nonebot_plugin_enatfrp/__init__.py
nonebot_plugin_enatfrp/api.py
nonebot_plugin_enatfrp/config.py
nonebot_plugin_enatfrp/exception.py
nonebot_plugin_enatfrp/tools.py
nonebot_plugin_enatfrp-0.3.0.dist-info/LICENSE
nonebot_plugin_enatfrp-0.3.0.dist-info/METADATA
nonebot_plugin_enatfrp-0.3.0.dist-info/WHEEL
nonebot_plugin_enatfrp-0.3.0.dist-info/RECORD
