Metadata-Version: 2.1
Name: nonebot-plugin-enatfrp
Version: 0.3.0
Summary: SakuraFrp管理插件
License: MIT
Author: eya46
Author-email: 61458340+eya46@users.noreply.github.com
Requires-Python: >=3.9,<4.0
Classifier: License :: OSI Approved :: MIT License
Classifier: Programming Language :: Python :: 3
Classifier: Programming Language :: Python :: 3.9
Classifier: Programming Language :: Python :: 3.10
Classifier: Programming Language :: Python :: 3.11
Classifier: Programming Language :: Python :: 3.12
Requires-Dist: nonebot-plugin-alconna (>=0.52.2)
Requires-Dist: nonebot2[httpx] (>=2.3.0)
